<?xml version="1.0" encoding="utf-8" standalone="yes"?>
<!DOCTYPE ROOT PUBLIC "" ""[]>
<StackFile xmlns:r="reflection">
  <Node Name="Stream.Paint3" Fold="False">
    <Bee r:Type="VVVV.Schema.PassthroughBee" />
    <Children>
      <Item Name="Operator.Add" Fold="False">
        <Bee r:Type="VVVV.Schema.AddBee" />
        <Children>
          <Item Name="Effect.Color.Paint.AlphaBased" Fold="False">
            <Bee r:Type="VVVV.Schema.Block.Behavior.Effect.Color.Paint.AlphaBased">
              <Canvas>
                <Item>0, 0, 0, 1</Item>
                <Item>0, 0, 0, 1</Item>
                <Item>0, 0, 0, 1</Item>
                <Item>0, 0, 0, 1</Item>
                <Item>0, 0, 0, 1</Item>
                <Item>0, 0, 0, 1</Item>
                <Item>0, 0, 0, 1</Item>
                <Item>0, 0, 0, 1</Item>
                <Item>1.401298E-45, 0, 0, 1</Item>
                <Item>0, 0, 0, 1</Item>
                <Item>2.86688E-11, 2.867644E-15, 2.867644E-15, 1</Item>
                <Item>3.612173E-09, 3.613134E-13, 3.613134E-13, 1</Item>
                <Item>6.331774E-08, 6.333457E-12, 6.333457E-12, 1</Item>
                <Item>0.2371177, 6.109077E-05, 0.6107452, 1</Item>
                <Item>0.2654575, 9.984906E-05, 0.998225, 1</Item>
                <Item>0.3121496, 9.697381E-05, 0.9694803, 1</Item>
                <Item>3.732829E-10, 2.247491E-08, 2.150975E-08, 1</Item>
                <Item>0, 0, 0, 1</Item>
                <Item>0, 0, 0, 1</Item>
                <Item>0, 0, 0, 1</Item>
                <Item>0, 0, 0, 1</Item>
                <Item>0, 0, 0, 1</Item>
                <Item>0, 0, 0, 1</Item>
                <Item>0, 0, 0, 1</Item>
                <Item>0, 0, 0, 1</Item>
                <Item>0, 0, 0, 1</Item>
                <Item>0, 0, 0, 1</Item>
                <Item>0, 0, 0, 1</Item>
                <Item>0, 0, 0, 1</Item>
                <Item>0, 0, 0, 1</Item>
                <Item>0, 0, 0, 1</Item>
                <Item>0, 0, 0, 1</Item>
                <Item>0, 0, 0, 1</Item>
                <Item>0, 0, 0, 1</Item>
                <Item>0, 0, 0, 1</Item>
                <Item>8.163755E-14, 8.165926E-18, 8.165926E-18, 1</Item>
                <Item>5.380228E-13, 5.381662E-17, 5.381662E-17, 1</Item>
                <Item>1.15143E-07, 1.151737E-11, 1.151737E-11, 1</Item>
                <Item>0.2593597, 6.689814E-05, 0.6688035, 1</Item>
                <Item>0.2775863, 9.920371E-05, 0.9917733, 1</Item>
                <Item>0.3234661, 9.954653E-05, 0.9952006, 1</Item>
                <Item>1.83054E-11, 1.331778E-10, 1.265092E-10, 1</Item>
                <Item>0, 0, 0, 1</Item>
                <Item>0, 0, 0, 1</Item>
                <Item>0, 0, 0, 1</Item>
                <Item>0, 0, 0, 1</Item>
                <Item>0, 0, 0, 1</Item>
                <Item>0, 0, 0, 1</Item>
                <Item>0, 0, 0, 1</Item>
                <Item>0, 0, 0, 1</Item>
                <Item>0, 0, 0, 1</Item>
                <Item>0, 0, 0, 1</Item>
                <Item>0, 0, 0, 1</Item>
                <Item>0, 0, 0, 1</Item>
                <Item>0, 0, 0, 1</Item>
                <Item>0, 0, 0, 1</Item>
                <Item>0, 0, 0, 1</Item>
                <Item>0, 0, 0, 1</Item>
                <Item>0, 0, 0, 1</Item>
                <Item>0, 0, 0, 1</Item>
                <Item>2.128898E-05, 0.1072755, 0.2128332, 1</Item>
                <Item>3.038199E-17, 3.039007E-21, 3.039007E-21, 1</Item>
                <Item>0.0974374, 2.518097E-05, 0.2517427, 1</Item>
                <Item>0.1126317, 2.911584E-05, 0.291081, 1</Item>
                <Item>0.242482, 9.934948E-05, 0.9932306, 1</Item>
                <Item>0.3298382, 9.9125E-05, 0.9909863, 1</Item>
                <Item>1.06418E-11, 1.064463E-15, 1.064463E-15, 1</Item>
                <Item>0, 0, 0, 1</Item>
                <Item>0, 0, 0, 1</Item>
                <Item>0, 0, 0, 1</Item>
                <Item>0, 0, 0, 1</Item>
                <Item>0, 0, 0, 1</Item>
                <Item>0, 0, 0, 1</Item>
                <Item>0, 0, 0, 1</Item>
                <Item>0, 0, 0, 1</Item>
                <Item>0, 0, 0, 1</Item>
                <Item>0, 0, 0, 1</Item>
                <Item>0, 0, 0, 1</Item>
                <Item>0, 0, 0, 1</Item>
                <Item>0, 0, 0, 1</Item>
                <Item>0, 0, 0, 1</Item>
                <Item>0, 0, 0, 1</Item>
                <Item>0, 0, 0, 1</Item>
                <Item>0, 0, 0, 1</Item>
                <Item>0, 0, 0, 1</Item>
                <Item>3.921746E-05, 0.1979037, 0.3920704, 1</Item>
                <Item>1.777628E-10, 9.031039E-07, 1.777156E-06, 1</Item>
                <Item>0.03608834, 9.323638E-06, 0.09321158, 1</Item>
                <Item>0.3800216, 9.963445E-05, 0.9960795, 1</Item>
                <Item>0.2352566, 9.99701E-05, 0.9994351, 1</Item>
                <Item>0.2510364, 0.0001000165, 0.9998994, 1</Item>
                <Item>0.3166324, 9.288684E-05, 0.9286214, 1</Item>
                <Item>0, 0, 0, 1</Item>
                <Item>0, 0, 0, 1</Item>
                <Item>0, 0, 0, 1</Item>
                <Item>0, 0, 0, 1</Item>
                <Item>0, 0, 0, 1</Item>
                <Item>0, 0, 0, 1</Item>
                <Item>0, 0, 0, 1</Item>
                <Item>0, 0, 0, 1</Item>
                <Item>0, 0, 0, 1</Item>
                <Item>0, 0, 0, 1</Item>
                <Item>0, 0, 0, 1</Item>
                <Item>0, 0, 0, 1</Item>
                <Item>0, 0, 0, 1</Item>
                <Item>0, 0, 0, 1</Item>
                <Item>0, 0, 0, 1</Item>
                <Item>0, 0, 0, 1</Item>
                <Item>0, 0, 0, 1</Item>
                <Item>0, 0, 0, 1</Item>
                <Item>7.153174E-06, 0.03616429, 0.07151272, 1</Item>
                <Item>5.833662E-12, 2.960459E-08, 5.83211E-08, 1</Item>
                <Item>0.3888295, 9.786936E-05, 0.9784333, 1</Item>
                <Item>0.3637964, 9.766276E-05, 0.976368, 1</Item>
                <Item>0.2241642, 9.782451E-05, 0.9779849, 1</Item>
                <Item>0.333037, 9.97557E-05, 0.9972917, 1</Item>
                <Item>9.843316E-11, 9.84593E-15, 9.84593E-15, 1</Item>
                <Item>0, 0, 0, 1</Item>
                <Item>0, 0, 0, 1</Item>
                <Item>0, 0, 0, 1</Item>
                <Item>0, 0, 0, 1</Item>
                <Item>0, 0, 0, 1</Item>
                <Item>0, 0, 0, 1</Item>
                <Item>0, 0, 0, 1</Item>
                <Item>0, 0, 0, 1</Item>
                <Item>0, 0, 0, 1</Item>
                <Item>0, 0, 0, 1</Item>
                <Item>0, 0, 0, 1</Item>
                <Item>0, 0, 0, 1</Item>
                <Item>0, 0, 0, 1</Item>
                <Item>0, 0, 0, 1</Item>
                <Item>0, 0, 0, 1</Item>
                <Item>0, 0, 0, 1</Item>
                <Item>0, 0, 0, 1</Item>
                <Item>0, 0, 0, 1</Item>
                <Item>7.166656E-06, 0.03604103, 0.0716459, 1</Item>
                <Item>6.631658E-12, 3.152763E-08, 6.62989E-08, 1</Item>
                <Item>0.4157192, 9.999827E-05, 0.9997168, 1</Item>
                <Item>0.2978624, 0.0001000165, 0.999899, 1</Item>
                <Item>0.2246561, 0.0001000427, 0.9998999, 1</Item>
                <Item>0.3241116, 0.0001000166, 0.9998996, 1</Item>
                <Item>0.332757, 9.996179E-05, 0.9993521, 1</Item>
                <Item>0, 0, 0, 1</Item>
                <Item>0, 0, 0, 1</Item>
                <Item>0, 0, 0, 1</Item>
                <Item>0, 0, 0, 1</Item>
                <Item>0, 0, 0, 1</Item>
                <Item>0, 0, 0, 1</Item>
                <Item>0, 0, 0, 1</Item>
                <Item>0, 0, 0, 1</Item>
                <Item>0, 0, 0, 1</Item>
                <Item>0, 0, 0, 1</Item>
                <Item>0, 0, 0, 1</Item>
                <Item>0, 0, 0, 1</Item>
                <Item>0, 0, 0, 1</Item>
                <Item>0, 0, 0, 1</Item>
                <Item>0, 0, 0, 1</Item>
                <Item>0, 0, 0, 1</Item>
                <Item>0, 0, 0, 1</Item>
                <Item>0, 0, 0, 1</Item>
                <Item>6.58173E-11, 6.583478E-15, 6.583478E-15, 1</Item>
                <Item>1.692914E-12, 7.370717E-09, 1.692464E-08, 1</Item>
                <Item>0.3981409, 9.508259E-05, 0.9505731, 1</Item>
                <Item>0.3893973, 9.948639E-05, 0.9945995, 1</Item>
                <Item>3.746154E-18, 5.937622E-17, 7.696708E-17, 1</Item>
                <Item>0, 0, 0, 1</Item>
                <Item>0, 0, 0, 1</Item>
                <Item>0, 0, 0, 1</Item>
                <Item>0, 0, 0, 1</Item>
                <Item>0, 0, 0, 1</Item>
              </Canvas>
            </Bee>
            <Children>
              <Item Name="Operator.Multiply" Fold="False">
                <Bee r:Type="VVVV.Schema.MultiplyBee" />
                <Children>
                  <Item Name="Effect.Color.Alpha.AsAlpha" Fold="False">
                    <Bee r:Type="VVVV.Schema.Block.Behavior.Effect.Color.Alpha.AsAlpha" />
                    <Children>
                      <Item Name="Operator.Multiply" Fold="False">
                        <Bee r:Type="VVVV.Schema.MultiplyBee" />
                        <Children>
                          <Item Name="Source.Color.Pixel.Distance" Fold="False">
                            <Bee r:Type="VVVV.Schema.Block.Behavior.Source.Color.Pixel.Distance" />
                            <Children />
                            <Properties>
                              <Properties>
                                <Item Key="Target/Local">
                                  <Value r:Type="System.Boolean">True</Value>
                                </Item>
                                <Item Key="Radius">
                                  <Value r:Type="System.Single">0.038</Value>
                                </Item>
                                <Item Key="Fixture">
                                  <Value r:Type="System.String">External</Value>
                                </Item>
                              </Properties>
                            </Properties>
                            <Drivers>
                              <Item Key="Radius">
                                <Value Name="Radius">
                                  <State>
                                    <Properties>
                                      <Item Key="Value">
                                        <Value r:Type="System.Single">0</Value>
                                      </Item>
                                    </Properties>
                                  </State>
                                  <Root_Node Name="Value" Fold="False">
                                    <Bee r:Type="VVVV.Schema.PassthroughBee" />
                                    <Children>
                                      <Item Name="Source.Value.OpenVR.Controller.Trigger" Fold="False">
                                        <Bee r:Type="VVVV.Schema.Block.Behavior.Source.Value.OpenVR.Controller.Trigger_1" />
                                        <Children />
                                        <Properties />
                                        <Drivers />
                                      </Item>
                                    </Children>
                                    <Properties />
                                    <Drivers />
                                  </Root_Node>
                                  <Setup>
                                    <Properties>
                                      <Item Key="FromMax">
                                        <Value r:Type="System.Single">1</Value>
                                      </Item>
                                      <Item Key="FromMin">
                                        <Value r:Type="System.Single">0</Value>
                                      </Item>
                                      <Item Key="ToMax">
                                        <Value r:Type="System.Single">0.158</Value>
                                      </Item>
                                      <Item Key="ToMin">
                                        <Value r:Type="System.Single">0.038</Value>
                                      </Item>
                                    </Properties>
                                  </Setup>
                                </Value>
                              </Item>
                            </Drivers>
                          </Item>
                          <Item Name="Convert.Color.FromValue" Fold="False">
                            <Bee r:Type="VVVV.Schema.Block.Behavior.Convert.Color.FromValue_1" />
                            <Children>
                              <Item Name="Operator.Add" Fold="False">
                                <Bee r:Type="VVVV.Schema.AddBee" />
                                <Children>
                                  <Item Name="Source.Value.OpenVR.Controller.Grip" Fold="False">
                                    <Bee r:Type="VVVV.Schema.Block.Behavior.Source.Value.OpenVR.Controller.Grip" />
                                    <Children />
                                    <Properties />
                                    <Drivers />
                                  </Item>
                                  <Item Name="Source.Value.OpenVR.Controller.Trigger" Fold="False">
                                    <Bee r:Type="VVVV.Schema.Block.Behavior.Source.Value.OpenVR.Controller.Trigger_1" />
                                    <Children />
                                    <Properties />
                                    <Drivers />
                                  </Item>
                                </Children>
                                <Properties />
                                <Drivers />
                              </Item>
                            </Children>
                            <Properties />
                            <Drivers />
                          </Item>
                        </Children>
                        <Properties />
                        <Drivers />
                      </Item>
                    </Children>
                    <Properties />
                    <Drivers />
                  </Item>
                  <Item Name="Operator.Multiply" Fold="False">
                    <Bee r:Type="VVVV.Schema.MultiplyBee" />
                    <Children>
                      <Item Name="Effect.Color.Hue.Rotate" Fold="False">
                        <Bee r:Type="VVVV.Schema.Block.Behavior.Effect.Color.Hue.Rotate_1" />
                        <Children>
                          <Item Name="Source.Color.Color" Fold="False">
                            <Bee r:Type="VVVV.Schema.FillColorBee" />
                            <Children />
                            <Properties>
                              <Properties>
                                <Item Key="Color">
                                  <Value r:Type="SharpDX.Color4">0.9999, 0.0001, 0.0001, 1</Value>
                                </Item>
                              </Properties>
                            </Properties>
                            <Drivers />
                          </Item>
                        </Children>
                        <Properties>
                          <Properties>
                            <Item Key="Value">
                              <Value r:Type="System.Single">0</Value>
                            </Item>
                          </Properties>
                        </Properties>
                        <Drivers>
                          <Item Key="Value">
                            <Value Name="Value">
                              <State>
                                <Properties>
                                  <Item Key="Value">
                                    <Value r:Type="System.Single">0</Value>
                                  </Item>
                                </Properties>
                              </State>
                              <Root_Node Name="Value" Fold="False">
                                <Bee r:Type="VVVV.Schema.PassthroughBee" />
                                <Children>
                                  <Item Name="Source.Value.OpenVR.Controller.TouchpadPolar" Fold="False">
                                    <Bee r:Type="VVVV.Schema.Block.Behavior.Source.Value.OpenVR.Controller.TouchpadPolar" />
                                    <Children />
                                    <Properties />
                                    <Drivers />
                                  </Item>
                                </Children>
                                <Properties />
                                <Drivers />
                              </Root_Node>
                              <Setup>
                                <Properties>
                                  <Item Key="FromMax">
                                    <Value r:Type="System.Single">1</Value>
                                  </Item>
                                  <Item Key="FromMin">
                                    <Value r:Type="System.Single">0</Value>
                                  </Item>
                                  <Item Key="ToMax">
                                    <Value r:Type="System.Single">1</Value>
                                  </Item>
                                  <Item Key="ToMin">
                                    <Value r:Type="System.Single">0</Value>
                                  </Item>
                                </Properties>
                              </Setup>
                            </Value>
                          </Item>
                        </Drivers>
                      </Item>
                      <Item Name="Convert.Color.FromValue" Fold="False">
                        <Bee r:Type="VVVV.Schema.Block.Behavior.Convert.Color.FromValue_1" />
                        <Children>
                          <Item Name="Source.Value.OpenVR.Controller.Grip" Fold="False">
                            <Bee r:Type="VVVV.Schema.Block.Behavior.Source.Value.OpenVR.Controller.Grip" />
                            <Children />
                            <Properties />
                            <Drivers />
                          </Item>
                        </Children>
                        <Properties />
                        <Drivers />
                      </Item>
                    </Children>
                    <Properties />
                    <Drivers />
                  </Item>
                </Children>
                <Properties />
                <Drivers />
              </Item>
            </Children>
            <Properties>
              <Properties>
                <Item Key="Clear">
                  <Value r:Type="System.Boolean">False</Value>
                </Item>
              </Properties>
            </Properties>
            <Drivers />
          </Item>
        </Children>
        <Properties />
        <Drivers />
      </Item>
    </Children>
    <Properties />
    <Drivers />
  </Node>
  <Descriptor Name="Stream.Paint3" />
</StackFile>